odoo9_addon_web_access_rule_buttons-9.0.1.0.0.99.dev10-py2.7-nspkg.pth
odoo9_addon_web_access_rule_buttons-9.0.1.0.0.99.dev10.dist-info/METADATA
odoo9_addon_web_access_rule_buttons-9.0.1.0.0.99.dev10.dist-info/RECORD
odoo9_addon_web_access_rule_buttons-9.0.1.0.0.99.dev10.dist-info/WHEEL
odoo9_addon_web_access_rule_buttons-9.0.1.0.0.99.dev10.dist-info/namespace_packages.txt
odoo9_addon_web_access_rule_buttons-9.0.1.0.0.99.dev10.dist-info/top_level.txt
odoo_addons/web_access_rule_buttons/README.rst
odoo_addons/web_access_rule_buttons/__init__.py
odoo_addons/web_access_rule_buttons/__openerp__.py
odoo_addons/web_access_rule_buttons/models.py
odoo_addons/web_access_rule_buttons/i18n/ca.po
odoo_addons/web_access_rule_buttons/i18n/de.po
odoo_addons/web_access_rule_buttons/i18n/pt_BR.po
odoo_addons/web_access_rule_buttons/static/description/icon.png
odoo_addons/web_access_rule_buttons/static/src/js/web_access_rule_buttons.js
odoo_addons/web_access_rule_buttons/views/web_access_rule_buttons.xml
