Metadata-Version: 2.1
Name: odoo9-addon-web-access-rule-buttons
Version: 9.0.1.0.0.99.dev10
Summary: Disable Edit button if access rules prevent this action
Home-page: http://www.camptocamp.com
Author: Camptocamp,Odoo Community Association (OCA)
Author-email: support@odoo-community.org
License: AGPL-3
Platform: UNKNOWN
Classifier: Programming Language :: Python
Classifier: Framework :: Odoo
Classifier: License :: OSI Approved :: GNU Affero General Public License v3
Requires-Python: ~=2.7
Requires-Dist: odoo (<9.1a,>=9.0a)
